{
  "motos": [
    {
      "id": 1,
      "content": "https://raw.githubusercontent.com/pac13/motos-img/master/ninja-300.png",
      "name": "Ninja 300",
      "description": "Description about motorcycle...",
      "city": "Bogotá",
      "brand": "Kawasaki",
      "price": "1500"
    },
    {
      "id": 2,
      "content": "https://raw.githubusercontent.com/pac13/motos-img/master/z400.png",
      "name": "z400",
      "description": "Description about motorcycle...",
      "city": "Medellín",
      "brand": "Kawasaki",
      "price": "2900"
    },
    {
      "id": 3,
      "content": "https://raw.githubusercontent.com/pac13/motos-img/master/ninja-400.png",
      "name": "Ninja 400",
      "description": "Description about motorcycle...",
      "city": "Cúcuta",
      "brand": "Kawasaki",
      "price": "3200"
    },
    {
      "id": 4,
      "content": "https://raw.githubusercontent.com/pac13/motos-img/master/ninja-zx6r.png",
      "name": "Ninja Zx6r",
      "description": "Description about motorcycle...",
      "city": "Cartagena",
      "brand": "Kawasaki",
      "price": "3500"
    },
    {
      "id": 5,
      "content": "https://raw.githubusercontent.com/pac13/motos-img/master/z900.png",
      "name": "z900",
      "description": "Description about motorcycle...",
      "city": "Pereira",
      "brand": "Kawasaki",
      "price": "5500"
    },
    {
      "id": 6,
      "content": "https://raw.githubusercontent.com/pac13/motos-img/master/zx10r.png",
      "name": "Ninja Zx10r",
      "description": "Description about motorcycle...",
      "city": "Tunja",
      "brand": "Kawasaki",
      "price": "9500"
    },
    {
      "id": 7,
      "content": "https://raw.githubusercontent.com/pac13/motos-img/master/zh2.png",
      "name": "Zh2",
      "description": "Description about motorcycle...",
      "city": "Villavicencio",
      "brand": "Kawasaki",
      "price": "12000"
    },
    {
      "id": 8,
      "content": "https://raw.githubusercontent.com/pac13/motos-img/master/apache-rr-310.png",
      "name": "Apache RR 310",
      "description": "Description about motorcycle...",
      "city": "Bogotá",
      "brand": "TVS",
      "price": "1500"
    },
    {
      "id": 9,
      "content": "https://raw.githubusercontent.com/pac13/motos-img/master/bmw-310-gs.png",
      "name": "BMW 310 GS",
      "description": "Description about motorcycle...",
      "city": "Medellín",
      "brand": "BMW",
      "price": "2200"
    },
    {
      "id": 10,
      "content": "https://raw.githubusercontent.com/pac13/motos-img/master/bmw-310-r-transformed.png",
      "name": "BMW 310 R",
      "description": "Description about motorcycle...",
      "city": "Medellín",
      "brand": "BMW",
      "price": "2000"
    },
    {
      "id": 11,
      "content": "https://raw.githubusercontent.com/pac13/motos-img/master/bmw-f-900-r.png",
      "name": "BMW F 900 R",
      "description": "Description about motorcycle...",
      "city": "Bogotá",
      "brand": "BMW",
      "price": "6200"
    },
    {
      "id": 12,
      "content": "https://raw.githubusercontent.com/pac13/motos-img/master/bmw-s-1000-rr.png",
      "name": "BMW S 1000 RR",
      "description": "Description about motorcycle...",
      "city": "Girardot",
      "brand": "BMW",
      "price": "9200"
    },
    {
      "id": 13,
      "content": "https://raw.githubusercontent.com/pac13/motos-img/master/duke-390.png",
      "name": "Duke 390",
      "description": "Description about motorcycle...",
      "city": "Cartagena",
      "brand": "KTM",
      "price": "3200"
    },
    {
      "id": 14,
      "content": "https://raw.githubusercontent.com/pac13/motos-img/master/gsxs-750.png",
      "name": "GSXS 750",
      "description": "Description about motorcycle...",
      "city": "Santander",
      "brand": "Suzuki",
      "price": "5800"
    },
    {
      "id": 15,
      "content": "https://raw.githubusercontent.com/pac13/motos-img/master/ktm-790-duke.png",
      "name": "Duke 790",
      "description": "Description about motorcycle...",
      "city": "Cúcuta",
      "brand": "KTM",
      "price": "7200"
    },
    {
      "id": 16,
      "content": "https://raw.githubusercontent.com/pac13/motos-img/master/mt-03.png",
      "name": "Mt 03",
      "description": "Description about motorcycle...",
      "city": "Bogotá",
      "brand": "Yamaha",
      "price": "1900"
    },
    {
      "id": 17,
      "content": "https://raw.githubusercontent.com/pac13/motos-img/master/mt-07.png",
      "name": "Mt 07",
      "description": "Description about motorcycle...",
      "city": "Barranquilla",
      "brand": "Yamaha",
      "price": "4000"
    },
    {
      "id": 18,
      "content": "https://raw.githubusercontent.com/pac13/motos-img/master/mt-09.png",
      "name": "Mt 09",
      "description": "Description about motorcycle...",
      "city": "Cali",
      "brand": "Yamaha",
      "price": "6200"
    },
    {
      "id": 19,
      "content": "https://raw.githubusercontent.com/pac13/motos-img/master/mt-10.png",
      "name": "Mt 10",
      "description": "Description about motorcycle...",
      "city": "Bogotá",
      "brand": "Yamaha",
      "price": "8500"
    },
    {
      "id": 20,
      "content": "https://raw.githubusercontent.com/pac13/motos-img/master/super-duke-1290.png",
      "name": "Super Duke 1290",
      "description": "Description about motorcycle...",
      "city": "Villavicencio",
      "brand": "KTM",
      "price": "10500"
    },
    {
      "id": 21,
      "content": "https://raw.githubusercontent.com/pac13/motos-img/master/yamaha-r1m.png",
      "name": "R1M",
      "description": "Description about motorcycle...",
      "city": "Medellín",
      "brand": "Yamaha",
      "price": "9000"
    },
    {
      "id": 22,
      "content": "https://raw.githubusercontent.com/pac13/motos-img/master/yamaha-r3.png",
      "name": "R3",
      "description": "Description about motorcycle...",
      "city": "Cali",
      "brand": "Yamaha",
      "price": "2000"
    },
    {
      "id": 23,
      "content": "https://raw.githubusercontent.com/pac13/motos-img/master/yamaha-r6.png",
      "name": "R6",
      "description": "Description about motorcycle...",
      "city": "Bogotá",
      "brand": "Yamaha",
      "price": "2900"
    },
    {
      "id": 24,
      "content": "https://raw.githubusercontent.com/pac13/motos-img/master/yamaha-r7.png",
      "name": "R7",
      "description": "Description about motorcycle...",
      "city": "Girardot",
      "brand": "Yamaha",
      "price": "3900"
    },
    {
      "id": 1684682472442,
      "content": "https://www.auteco.com.co/wp-content/uploads/2022/04/RC_200_NG_2022_BLANCA_360_1.png",
      "name": "Rc 200",
      "description": "Description about motorcycle",
      "city": "Bucaramanga",
      "brand": "Suzuki",
      "price": "2000"
    }
  ]
}
